vitess/__init__.py
vitess/base.py
vitess/features.py
django_vitess-0.0.2.dist-info/LICENSE
django_vitess-0.0.2.dist-info/METADATA
django_vitess-0.0.2.dist-info/WHEEL
django_vitess-0.0.2.dist-info/top_level.txt
django_vitess-0.0.2.dist-info/RECORD
